gcp_io/__init__.py
gcp_io/gcp_interface.py
gcp_io/utils.py
gcp_io_util-0.1.1.dist-info/METADATA
gcp_io_util-0.1.1.dist-info/WHEEL
gcp_io_util-0.1.1.dist-info/RECORD
