Metadata-Version: 2.1
Name: gcp-io-util
Version: 0.1.1
Summary: GCS io utility functions
License: MIT
Author: Carlos Alvarez
Author-email: candres.alv@gmail.com
Requires-Python: >=3.8,<4.0
Classifier: License :: OSI Approved :: MIT License
Classifier: Programming Language :: Python :: 3
Classifier: Programming Language :: Python :: 3.8
Classifier: Programming Language :: Python :: 3.9
Classifier: Programming Language :: Python :: 3.10
Classifier: Programming Language :: Python :: 3.11
Classifier: Programming Language :: Python :: 3.12
Requires-Dist: google-cloud-storage (>=2.18.2,<3.0.0)
Requires-Dist: imageio (<=2.10.2)
Requires-Dist: imageio-ffmpeg (<=0.4.5)
Requires-Dist: numpy (<2.0.0)
Requires-Dist: pyyaml (>=6.0.2,<7.0.0)
